redys/__init__.py
redys/redys.py
redys/servone.py
redys/v2.py
redys-0.9.20.dist-info/LICENSE
redys-0.9.20.dist-info/METADATA
redys-0.9.20.dist-info/WHEEL
redys-0.9.20.dist-info/RECORD
