Metadata-Version: 2.1
Name: redys
Version: 0.9.20
Summary: A simple redis-like in pure python3, fully asyncio compliant
Home-page: https://github.com/manatlan/redys
License: MIT
Keywords: python3,redis,pickle,asyncio,queue,cache,set,pubsub,sync,async
Author: manatlan
Author-email: manatlan@gmail.com
Requires-Python: >=3.7,<4.0
Classifier: License :: OSI Approved :: MIT License
Classifier: Operating System :: OS Independent
Classifier: Programming Language :: Python :: 3
Classifier: Programming Language :: Python :: 3.7
Classifier: Programming Language :: Python :: 3.8
Classifier: Programming Language :: Python :: 3.9
Classifier: Programming Language :: Python :: 3.10
Classifier: Programming Language :: Python :: 3.11
Classifier: Topic :: Software Development :: Build Tools
Classifier: Topic :: Software Development :: Libraries :: Python Modules
Project-URL: Documentation, https://github.com/manatlan/redys
Project-URL: Repository, https://github.com/manatlan/redys
